MANIFEST.in
README.md
setup.py
mdlib/__init__.py
mdlib.egg-info/PKG-INFO
mdlib.egg-info/SOURCES.txt
mdlib.egg-info/dependency_links.txt
mdlib.egg-info/top_level.txt
mdlib/logger/__init__.py
mdlib/logger/logger.py
mdlib/mdtree/__init__.py
mdlib/mdtree/mdtree.py