Metadata-Version: 2.1
Name: mdlib
Version: 0.1.1
Summary: A lib for markdown.
Home-page: https://github.com/Lavender-Tree/mdlib
Author: Lavender Tree
Author-email: lavender.tree9988@gmail.com
License: MIT License
Keywords: markdown
Platform: any
